<?xml version="1.0" encoding="UTF-8"?>
<!-- Created with TexturePacker https://www.codeandweb.com/texturepacker -->
<!-- $TexturePacker:SmartUpdate:2d43a788dd2e758af89ea0753be93482:f8a7fcb4024c840ad7a140492acb2ff9:5f4ebb1f0aaf211a94c4dbf24a458bb5$ -->
<TextureAtlas imagePath="Sans.png" width="4083" height="4018">
    <SubTexture name="Down 02 instance 10000" x="3294" y="3404" rotated="true" width="456" height="468" frameX="0" frameY="-25" frameWidth="504" frameHeight="481"/>
    <SubTexture name="Down 02 instance 10001" x="3253" y="2929" width="453" height="473" frameX="-7" frameY="-8" frameWidth="504" frameHeight="481"/>
    <SubTexture name="Down 02 instance 10002" x="3253" y="2929" width="453" height="473" frameX="-7" frameY="-8" frameWidth="504" frameHeight="481"/>
    <SubTexture name="Down 02 instance 10003" x="2960" y="491" width="451" height="481" frameX="-8" frameY="0" frameWidth="504" frameHeight="481"/>
    <SubTexture name="Down 02 instance 10004" x="2960" y="491" width="451" height="481" frameX="-8" frameY="0" frameWidth="504" frameHeight="481"/>
    <SubTexture name="Down 02 instance 10005" x="3634" y="1472" width="448" height="481" frameX="-10" frameY="0" frameWidth="504" frameHeight="481"/>
    <SubTexture name="Down 02 instance 10006" x="3634" y="1472" width="448" height="481" frameX="-10" frameY="0" frameWidth="504" frameHeight="481"/>
    <SubTexture name="Down 02 instance 10007" x="1123" y="1" width="502" height="481" frameX="-2" frameY="0" frameWidth="504" frameHeight="481"/>
    <SubTexture name="Down 02 instance 10008" x="1123" y="1" width="502" height="481" frameX="-2" frameY="0" frameWidth="504" frameHeight="481"/>
    <SubTexture name="Down instance 10000" x="3294" y="3404" rotated="true" width="456" height="468" frameX="0" frameY="-25" frameWidth="504" frameHeight="481"/>
    <SubTexture name="Down instance 10001" x="3253" y="2929" width="453" height="473" frameX="-7" frameY="-8" frameWidth="504" frameHeight="481"/>
    <SubTexture name="Down instance 10002" x="3253" y="2929" width="453" height="473" frameX="-7" frameY="-8" frameWidth="504" frameHeight="481"/>
    <SubTexture name="Down instance 10003" x="3224" y="2445" width="451" height="482" frameX="-8" frameY="0" frameWidth="504" frameHeight="482"/>
    <SubTexture name="Down instance 10004" x="3224" y="2445" width="451" height="482" frameX="-8" frameY="0" frameWidth="504" frameHeight="482"/>
    <SubTexture name="Down instance 10005" x="3634" y="1472" width="448" height="481" frameX="-10" frameY="0" frameWidth="504" frameHeight="481"/>
    <SubTexture name="Down instance 10006" x="3634" y="1472" width="448" height="481" frameX="-10" frameY="0" frameWidth="504" frameHeight="481"/>
    <SubTexture name="Down instance 10007" x="1" y="3036" rotated="true" width="482" height="502" frameX="-2" frameY="0" frameWidth="504" frameHeight="482"/>
    <SubTexture name="Down instance 10008" x="1" y="3036" rotated="true" width="482" height="502" frameX="-2" frameY="0" frameWidth="504" frameHeight="482"/>
    <SubTexture name="Left 02 instance 10000" x="1" y="1" width="573" height="481" frameX="0" frameY="-14" frameWidth="573" frameHeight="495"/>
    <SubTexture name="Left 02 instance 10001" x="1" y="484" width="532" height="495" frameX="-25" frameY="0" frameWidth="573" frameHeight="495"/>
    <SubTexture name="Left 02 instance 10002" x="1" y="484" width="532" height="495" frameX="-25" frameY="0" frameWidth="573" frameHeight="495"/>
    <SubTexture name="Left 02 instance 10003" x="1" y="981" width="512" height="495" frameX="-37" frameY="0" frameWidth="573" frameHeight="495"/>
    <SubTexture name="Left 02 instance 10004" x="1" y="981" width="512" height="495" frameX="-37" frameY="0" frameWidth="573" frameHeight="495"/>
    <SubTexture name="Left 02 instance 10005" x="2633" y="1" rotated="true" width="495" height="488" frameX="-52" frameY="0" frameWidth="573" frameHeight="495"/>
    <SubTexture name="Left 02 instance 10006" x="2633" y="1" rotated="true" width="495" height="488" frameX="-52" frameY="0" frameWidth="573" frameHeight="495"/>
    <SubTexture name="Left 02 instance 10007" x="485" y="2506" width="475" height="495" frameX="-57" frameY="0" frameWidth="573" frameHeight="495"/>
    <SubTexture name="Left 02 instance 10008" x="485" y="2506" width="475" height="495" frameX="-57" frameY="0" frameWidth="573" frameHeight="495"/>
    <SubTexture name="Left 02 instance 10009" x="3677" y="2433" width="405" height="476" frameX="-56" frameY="-19" frameWidth="573" frameHeight="495"/>
    <SubTexture name="Left 02 instance 10010" x="3677" y="2433" width="405" height="476" frameX="-56" frameY="-19" frameWidth="573" frameHeight="495"/>
    <SubTexture name="Left instance 10000" x="1" y="2520" rotated="true" width="482" height="514" frameX="0" frameY="-13" frameWidth="550" frameHeight="495"/>
    <SubTexture name="Left instance 10001" x="3130" y="1" rotated="true" width="495" height="487" frameX="-26" frameY="0" frameWidth="550" frameHeight="495"/>
    <SubTexture name="Left instance 10002" x="3130" y="1" rotated="true" width="495" height="487" frameX="-26" frameY="0" frameWidth="550" frameHeight="495"/>
    <SubTexture name="Left instance 10003" x="499" y="3499" width="467" height="495" frameX="-38" frameY="0" frameWidth="550" frameHeight="495"/>
    <SubTexture name="Left instance 10004" x="499" y="3499" width="467" height="495" frameX="-38" frameY="0" frameWidth="550" frameHeight="495"/>
    <SubTexture name="Left instance 10005" x="515" y="981" width="450" height="495" frameX="-53" frameY="0" frameWidth="550" frameHeight="495"/>
    <SubTexture name="Left instance 10006" x="515" y="981" width="450" height="495" frameX="-53" frameY="0" frameWidth="550" frameHeight="495"/>
    <SubTexture name="Left instance 10007" x="535" y="484" width="446" height="495" frameX="-57" frameY="0" frameWidth="550" frameHeight="495"/>
    <SubTexture name="Left instance 10008" x="535" y="484" width="446" height="495" frameX="-57" frameY="0" frameWidth="550" frameHeight="495"/>
    <SubTexture name="Left instance 10009" x="485" y="3003" rotated="true" width="477" height="494" frameX="-56" frameY="-18" frameWidth="550" frameHeight="495"/>
    <SubTexture name="Left instance 10010" x="485" y="3003" rotated="true" width="477" height="494" frameX="-56" frameY="-18" frameWidth="550" frameHeight="495"/>
    <SubTexture name="Right 02 instance 10000" x="2841" y="3448" width="451" height="490" frameX="-19" frameY="-4" frameWidth="494" frameHeight="494"/>
    <SubTexture name="Right 02 instance 10001" x="1801" y="1467" width="439" height="494" frameX="-10" frameY="0" frameWidth="494" frameHeight="494"/>
    <SubTexture name="Right 02 instance 10002" x="1801" y="1467" width="439" height="494" frameX="-10" frameY="0" frameWidth="494" frameHeight="494"/>
    <SubTexture name="Right 02 instance 10003" x="1868" y="1963" width="433" height="494" frameX="-5" frameY="0" frameWidth="494" frameHeight="494"/>
    <SubTexture name="Right 02 instance 10004" x="1868" y="1963" width="433" height="494" frameX="-5" frameY="0" frameWidth="494" frameHeight="494"/>
    <SubTexture name="Right 02 instance 10005" x="1870" y="2459" width="439" height="494" frameX="-1" frameY="0" frameWidth="494" frameHeight="494"/>
    <SubTexture name="Right 02 instance 10006" x="1870" y="2459" width="439" height="494" frameX="-1" frameY="0" frameWidth="494" frameHeight="494"/>
    <SubTexture name="Right 02 instance 10007" x="1870" y="2459" width="439" height="494" frameX="-1" frameY="0" frameWidth="494" frameHeight="494"/>
    <SubTexture name="Right 02 instance 10008" x="1910" y="2955" width="439" height="494" frameX="0" frameY="0" frameWidth="494" frameHeight="494"/>
    <SubTexture name="Right 02 instance 10009" x="1910" y="2955" width="439" height="494" frameX="0" frameY="0" frameWidth="494" frameHeight="494"/>
    <SubTexture name="Right 02 instance 10010" x="1910" y="2955" width="439" height="494" frameX="0" frameY="0" frameWidth="494" frameHeight="494"/>
    <SubTexture name="Right 02 instance 10011" x="983" y="484" width="494" height="488" frameX="0" frameY="-6" frameWidth="494" frameHeight="494"/>
    <SubTexture name="Right 02 instance 10012" x="983" y="484" width="494" height="488" frameX="0" frameY="-6" frameWidth="494" frameHeight="494"/>
    <SubTexture name="Right instance 10000" x="1915" y="3451" width="451" height="494" frameX="-14" frameY="0" frameWidth="494" frameHeight="494"/>
    <SubTexture name="Right instance 10001" x="2242" y="1467" width="439" height="494" frameX="-10" frameY="0" frameWidth="494" frameHeight="494"/>
    <SubTexture name="Right instance 10002" x="2242" y="1467" width="439" height="494" frameX="-10" frameY="0" frameWidth="494" frameHeight="494"/>
    <SubTexture name="Right instance 10003" x="2303" y="1963" width="434" height="494" frameX="-4" frameY="0" frameWidth="494" frameHeight="494"/>
    <SubTexture name="Right instance 10004" x="2303" y="1963" width="434" height="494" frameX="-4" frameY="0" frameWidth="494" frameHeight="494"/>
    <SubTexture name="Right instance 10005" x="2311" y="2459" width="439" height="494" frameX="0" frameY="0" frameWidth="494" frameHeight="494"/>
    <SubTexture name="Right instance 10006" x="2311" y="2459" width="439" height="494" frameX="0" frameY="0" frameWidth="494" frameHeight="494"/>
    <SubTexture name="Right instance 10007" x="2351" y="2955" width="438" height="494" frameX="0" frameY="0" frameWidth="494" frameHeight="494"/>
    <SubTexture name="Right instance 10008" x="2351" y="2955" width="438" height="494" frameX="0" frameY="0" frameWidth="494" frameHeight="494"/>
    <SubTexture name="Right instance 10009" x="1479" y="485" width="494" height="487" frameX="0" frameY="-7" frameWidth="494" frameHeight="494"/>
    <SubTexture name="Right instance 10010" x="1479" y="485" width="494" height="487" frameX="0" frameY="-7" frameWidth="494" frameHeight="494"/>
    <SubTexture name="Sans FNF 02 instance 10000" x="1975" y="485" width="487" height="485" frameX="0" frameY="-9" frameWidth="487" frameHeight="494"/>
    <SubTexture name="Sans FNF 02 instance 10001" x="1975" y="485" width="487" height="485" frameX="0" frameY="-9" frameWidth="487" frameHeight="494"/>
    <SubTexture name="Sans FNF 02 instance 10002" x="1440" y="974" width="476" height="491" frameX="-4" frameY="-3" frameWidth="487" frameHeight="494"/>
    <SubTexture name="Sans FNF 02 instance 10003" x="1440" y="974" width="476" height="491" frameX="-4" frameY="-3" frameWidth="487" frameHeight="494"/>
    <SubTexture name="Sans FNF 02 instance 10004" x="1975" y="972" width="474" height="493" frameX="-5" frameY="-1" frameWidth="487" frameHeight="494"/>
    <SubTexture name="Sans FNF 02 instance 10005" x="1975" y="972" width="474" height="493" frameX="-5" frameY="-1" frameWidth="487" frameHeight="494"/>
    <SubTexture name="Sans FNF 02 instance 10006" x="1440" y="3466" width="473" height="494" frameX="-7" frameY="0" frameWidth="487" frameHeight="494"/>
    <SubTexture name="Sans FNF 02 instance 10007" x="1440" y="3466" width="473" height="494" frameX="-7" frameY="0" frameWidth="487" frameHeight="494"/>
    <SubTexture name="Sans FNF 02 instance 10008" x="2368" y="3451" width="471" height="494" frameX="-8" frameY="0" frameWidth="487" frameHeight="494"/>
    <SubTexture name="Sans FNF 02 instance 10009" x="2368" y="3451" width="471" height="494" frameX="-8" frameY="0" frameWidth="487" frameHeight="494"/>
    <SubTexture name="Sans FNF 02 instance 10010" x="3406" y="999" rotated="true" width="494" height="471" frameX="-9" frameY="0" frameWidth="487" frameHeight="494"/>
    <SubTexture name="Sans FNF 02 instance 10011" x="3406" y="999" rotated="true" width="494" height="471" frameX="-9" frameY="0" frameWidth="487" frameHeight="494"/>
    <SubTexture name="Sans FNF 02 instance 10012" x="2683" y="1466" width="470" height="494" frameX="-9" frameY="0" frameWidth="487" frameHeight="494"/>
    <SubTexture name="Sans FNF 02 instance 10013" x="2683" y="1466" width="470" height="494" frameX="-9" frameY="0" frameWidth="487" frameHeight="494"/>
    <SubTexture name="Sans FNF instance 10000" x="3413" y="526" rotated="true" width="495" height="471" frameX="-23" frameY="0" frameWidth="500" frameHeight="495"/>
    <SubTexture name="Sans FNF instance 10001" x="3413" y="526" rotated="true" width="495" height="471" frameX="-23" frameY="0" frameWidth="500" frameHeight="495"/>
    <SubTexture name="Sans FNF instance 10002" x="3413" y="526" rotated="true" width="495" height="471" frameX="-23" frameY="0" frameWidth="500" frameHeight="495"/>
    <SubTexture name="Sans FNF instance 10003" x="3155" y="1472" width="477" height="484" frameX="-23" frameY="-11" frameWidth="500" frameHeight="495"/>
    <SubTexture name="Sans FNF instance 10004" x="3155" y="1472" width="477" height="484" frameX="-23" frameY="-11" frameWidth="500" frameHeight="495"/>
    <SubTexture name="Sans FNF instance 10005" x="2739" y="1962" width="471" height="494" frameX="-25" frameY="-1" frameWidth="500" frameHeight="495"/>
    <SubTexture name="Sans FNF instance 10006" x="2739" y="1962" width="471" height="494" frameX="-25" frameY="-1" frameWidth="500" frameHeight="495"/>
    <SubTexture name="Sans FNF instance 10007" x="967" y="981" width="471" height="495" frameX="-23" frameY="0" frameWidth="500" frameHeight="495"/>
    <SubTexture name="Sans FNF instance 10008" x="967" y="981" width="471" height="495" frameX="-23" frameY="0" frameWidth="500" frameHeight="495"/>
    <SubTexture name="Sans FNF instance 10009" x="964" y="2987" width="471" height="495" frameX="-19" frameY="0" frameWidth="500" frameHeight="495"/>
    <SubTexture name="Sans FNF instance 10010" x="964" y="2987" width="471" height="495" frameX="-19" frameY="0" frameWidth="500" frameHeight="495"/>
    <SubTexture name="Sans FNF instance 10011" x="968" y="3484" width="470" height="495" frameX="-16" frameY="0" frameWidth="500" frameHeight="495"/>
    <SubTexture name="Sans FNF instance 10012" x="968" y="3484" width="470" height="495" frameX="-16" frameY="0" frameWidth="500" frameHeight="495"/>
    <SubTexture name="Sans FNF instance 10013" x="1329" y="1478" width="470" height="495" frameX="-14" frameY="0" frameWidth="500" frameHeight="495"/>
    <SubTexture name="Sans FNF instance 10014" x="1329" y="1478" width="470" height="495" frameX="-14" frameY="0" frameWidth="500" frameHeight="495"/>
    <SubTexture name="Sans FNF instance 10015" x="1395" y="1975" width="471" height="495" frameX="-11" frameY="0" frameWidth="500" frameHeight="495"/>
    <SubTexture name="Sans FNF instance 10016" x="1395" y="1975" width="471" height="495" frameX="-11" frameY="0" frameWidth="500" frameHeight="495"/>
    <SubTexture name="Sans FNF instance 10017" x="2922" y="974" width="482" height="484" frameX="0" frameY="-11" frameWidth="500" frameHeight="495"/>
    <SubTexture name="Sans FNF instance 10018" x="2922" y="974" width="482" height="484" frameX="0" frameY="-11" frameWidth="500" frameHeight="495"/>
    <SubTexture name="Sans FNF instance 10019" x="2451" y="972" width="469" height="492" frameX="-8" frameY="-3" frameWidth="500" frameHeight="495"/>
    <SubTexture name="Sans FNF instance 10020" x="2451" y="972" width="469" height="492" frameX="-8" frameY="-3" frameWidth="500" frameHeight="495"/>
    <SubTexture name="Sans FNF instance 10021" x="1397" y="2472" width="471" height="495" frameX="-11" frameY="0" frameWidth="500" frameHeight="495"/>
    <SubTexture name="Sans FNF instance 10022" x="1397" y="2472" width="471" height="495" frameX="-11" frameY="0" frameWidth="500" frameHeight="495"/>
    <SubTexture name="Sans FNF instance 10023" x="1397" y="2472" width="471" height="495" frameX="-11" frameY="0" frameWidth="500" frameHeight="495"/>
    <SubTexture name="Sans FNF instance 10024" x="1329" y="1478" width="470" height="495" frameX="-14" frameY="0" frameWidth="500" frameHeight="495"/>
    <SubTexture name="Sans FNF instance 10025" x="1329" y="1478" width="470" height="495" frameX="-14" frameY="0" frameWidth="500" frameHeight="495"/>
    <SubTexture name="Sans FNF instance 10026" x="1329" y="1478" width="470" height="495" frameX="-14" frameY="0" frameWidth="500" frameHeight="495"/>
    <SubTexture name="Sans FNF instance 10027" x="968" y="3484" width="470" height="495" frameX="-16" frameY="0" frameWidth="500" frameHeight="495"/>
    <SubTexture name="Sans FNF instance 10028" x="968" y="3484" width="470" height="495" frameX="-16" frameY="0" frameWidth="500" frameHeight="495"/>
    <SubTexture name="Sans FNF instance 10029" x="1437" y="2969" width="471" height="495" frameX="-19" frameY="0" frameWidth="500" frameHeight="495"/>
    <SubTexture name="Sans FNF instance 10030" x="1437" y="2969" width="471" height="495" frameX="-19" frameY="0" frameWidth="500" frameHeight="495"/>
    <SubTexture name="Switch to UT mode instance 10000" x="2752" y="2458" width="470" height="494" frameX="-42" frameY="0" frameWidth="545" frameHeight="494"/>
    <SubTexture name="Switch to UT mode instance 10001" x="2752" y="2458" width="470" height="494" frameX="-42" frameY="0" frameWidth="545" frameHeight="494"/>
    <SubTexture name="Switch to UT mode instance 10002" x="2791" y="2954" width="460" height="492" frameX="-47" frameY="-2" frameWidth="545" frameHeight="494"/>
    <SubTexture name="Switch to UT mode instance 10003" x="3635" y="1955" width="431" height="476" frameX="-54" frameY="-18" frameWidth="545" frameHeight="494"/>
    <SubTexture name="Switch to UT mode instance 10004" x="3635" y="1955" width="431" height="476" frameX="-54" frameY="-18" frameWidth="545" frameHeight="494"/>
    <SubTexture name="Switch to UT mode instance 10005" x="3212" y="1958" width="421" height="485" frameX="-58" frameY="-9" frameWidth="545" frameHeight="494"/>
    <SubTexture name="Switch to UT mode instance 10006" x="3212" y="1958" width="421" height="485" frameX="-58" frameY="-9" frameWidth="545" frameHeight="494"/>
    <SubTexture name="Switch to UT mode instance 10007" x="576" y="1" width="545" height="474" frameX="0" frameY="-20" frameWidth="545" frameHeight="494"/>
    <SubTexture name="Switch to UT mode instance 10008" x="1" y="1478" rotated="true" width="481" height="519" frameX="-18" frameY="-13" frameWidth="545" frameHeight="494"/>
    <SubTexture name="Switch to UT mode instance 10009" x="1" y="1478" rotated="true" width="481" height="519" frameX="-18" frameY="-13" frameWidth="545" frameHeight="494"/>
    <SubTexture name="Switch to UT mode instance 10010" x="1" y="1999" rotated="true" width="481" height="519" frameX="-21" frameY="-13" frameWidth="545" frameHeight="494"/>
    <SubTexture name="Switch to UT mode instance 10011" x="1" y="1999" rotated="true" width="481" height="519" frameX="-21" frameY="-13" frameWidth="545" frameHeight="494"/>
    <SubTexture name="Switch to UT mode instance 10012" x="1" y="1999" rotated="true" width="481" height="519" frameX="-21" frameY="-13" frameWidth="545" frameHeight="494"/>
    <SubTexture name="Switch to UT mode instance 10013" x="1" y="1999" rotated="true" width="481" height="519" frameX="-21" frameY="-13" frameWidth="545" frameHeight="494"/>
    <SubTexture name="Switch to UT mode instance 10014" x="1" y="1999" rotated="true" width="481" height="519" frameX="-21" frameY="-13" frameWidth="545" frameHeight="494"/>
    <SubTexture name="Switch to UT mode instance 10015" x="1" y="1999" rotated="true" width="481" height="519" frameX="-21" frameY="-13" frameWidth="545" frameHeight="494"/>
    <SubTexture name="Switch to UT mode instance 10016" x="1" y="1999" rotated="true" width="481" height="519" frameX="-21" frameY="-13" frameWidth="545" frameHeight="494"/>
    <SubTexture name="Switch to UT mode instance 10017" x="1" y="1999" rotated="true" width="481" height="519" frameX="-21" frameY="-13" frameWidth="545" frameHeight="494"/>
    <SubTexture name="Up 02 instance 10000" x="3627" y="1" width="452" height="523" frameX="-17" frameY="0" frameWidth="544" frameHeight="523"/>
    <SubTexture name="Up 02 instance 10001" x="484" y="2002" width="474" height="502" frameX="-5" frameY="-21" frameWidth="544" frameHeight="523"/>
    <SubTexture name="Up 02 instance 10002" x="484" y="2002" width="474" height="502" frameX="-5" frameY="-21" frameWidth="544" frameHeight="523"/>
    <SubTexture name="Up 02 instance 10003" x="1627" y="1" rotated="true" width="501" height="482" frameX="0" frameY="-22" frameWidth="544" frameHeight="523"/>
    <SubTexture name="Up 02 instance 10004" x="1627" y="1" rotated="true" width="501" height="482" frameX="0" frameY="-22" frameWidth="544" frameHeight="523"/>
    <SubTexture name="Up 02 instance 10005" x="2130" y="1" rotated="true" width="501" height="482" frameX="0" frameY="-22" frameWidth="544" frameHeight="523"/>
    <SubTexture name="Up 02 instance 10006" x="2130" y="1" rotated="true" width="501" height="482" frameX="0" frameY="-22" frameWidth="544" frameHeight="523"/>
    <SubTexture name="Up 02 instance 10007" x="1" y="3540" width="496" height="477" frameX="-48" frameY="-46" frameWidth="544" frameHeight="523"/>
    <SubTexture name="Up 02 instance 10008" x="1" y="3540" width="496" height="477" frameX="-48" frameY="-46" frameWidth="544" frameHeight="523"/>
    <SubTexture name="Up instance 10000" x="484" y="1478" width="411" height="522" frameX="-8" frameY="0" frameWidth="494" frameHeight="522"/>
    <SubTexture name="Up instance 10001" x="897" y="1478" width="430" height="502" frameX="0" frameY="-20" frameWidth="494" frameHeight="522"/>
    <SubTexture name="Up instance 10002" x="897" y="1478" width="430" height="502" frameX="0" frameY="-20" frameWidth="494" frameHeight="522"/>
    <SubTexture name="Up instance 10003" x="962" y="2485" width="433" height="500" frameX="0" frameY="-22" frameWidth="494" frameHeight="522"/>
    <SubTexture name="Up instance 10004" x="962" y="2485" width="433" height="500" frameX="0" frameY="-22" frameWidth="494" frameHeight="522"/>
    <SubTexture name="Up instance 10005" x="960" y="1982" width="433" height="501" frameX="0" frameY="-21" frameWidth="494" frameHeight="522"/>
    <SubTexture name="Up instance 10006" x="960" y="1982" width="433" height="501" frameX="0" frameY="-21" frameWidth="494" frameHeight="522"/>
    <SubTexture name="Up instance 10007" x="2464" y="491" width="494" height="477" frameX="0" frameY="-45" frameWidth="494" frameHeight="522"/>
    <SubTexture name="Up instance 10008" x="2464" y="491" width="494" height="477" frameX="0" frameY="-45" frameWidth="494" frameHeight="522"/>
</TextureAtlas>
